zup/__init__.py
zup/commands.py
zup/config.py
zup/error.py
zup/fetch.py
zup/host.py
zup/installs.py
zup/main.py
zup-0.1.6.dist-info/LICENSE
zup-0.1.6.dist-info/METADATA
zup-0.1.6.dist-info/WHEEL
zup-0.1.6.dist-info/entry_points.txt
zup-0.1.6.dist-info/top_level.txt
zup-0.1.6.dist-info/zip-safe
zup-0.1.6.dist-info/RECORD
