Metadata-Version: 2.1
Name: zup
Version: 0.1.6
Summary: Zig compiler multiplexer
Home-page: https://github.com/yamirui/zup
Author: yamirui
Author-email: yamirui.git@gmail.com
License: zlib
Keywords: zig
Platform: UNKNOWN
Classifier: Programming Language :: Python :: 3.8
Classifier: License :: OSI Approved :: zlib/libpng License
Classifier: Operating System :: OS Independent
Classifier: Topic :: System :: Installation/Setup
Classifier: Development Status :: 4 - Beta
Requires-Python: >=3.8
